azure/mgmt/deviceupdate/__init__.py
azure/mgmt/deviceupdate/_configuration.py
azure/mgmt/deviceupdate/_device_update_mgmt_client.py
azure/mgmt/deviceupdate/_patch.py
azure/mgmt/deviceupdate/_serialization.py
azure/mgmt/deviceupdate/_vendor.py
azure/mgmt/deviceupdate/_version.py
azure/mgmt/deviceupdate/py.typed
azure/mgmt/deviceupdate/aio/__init__.py
azure/mgmt/deviceupdate/aio/_configuration.py
azure/mgmt/deviceupdate/aio/_device_update_mgmt_client.py
azure/mgmt/deviceupdate/aio/_patch.py
azure/mgmt/deviceupdate/aio/_vendor.py
azure/mgmt/deviceupdate/aio/operations/__init__.py
azure/mgmt/deviceupdate/aio/operations/_accounts_operations.py
azure/mgmt/deviceupdate/aio/operations/_device_update_mgmt_client_operations.py
azure/mgmt/deviceupdate/aio/operations/_instances_operations.py
azure/mgmt/deviceupdate/aio/operations/_operations.py
azure/mgmt/deviceupdate/aio/operations/_patch.py
azure/mgmt/deviceupdate/aio/operations/_private_endpoint_connection_proxies_operations.py
azure/mgmt/deviceupdate/aio/operations/_private_endpoint_connections_operations.py
azure/mgmt/deviceupdate/aio/operations/_private_link_resources_operations.py
azure/mgmt/deviceupdate/models/__init__.py
azure/mgmt/deviceupdate/models/_device_update_mgmt_client_enums.py
azure/mgmt/deviceupdate/models/_models_py3.py
azure/mgmt/deviceupdate/models/_patch.py
azure/mgmt/deviceupdate/operations/__init__.py
azure/mgmt/deviceupdate/operations/_accounts_operations.py
azure/mgmt/deviceupdate/operations/_device_update_mgmt_client_operations.py
azure/mgmt/deviceupdate/operations/_instances_operations.py
azure/mgmt/deviceupdate/operations/_operations.py
azure/mgmt/deviceupdate/operations/_patch.py
azure/mgmt/deviceupdate/operations/_private_endpoint_connection_proxies_operations.py
azure/mgmt/deviceupdate/operations/_private_endpoint_connections_operations.py
azure/mgmt/deviceupdate/operations/_private_link_resources_operations.py
azure_mgmt_deviceupdate-1.1.0.dist-info/LICENSE
azure_mgmt_deviceupdate-1.1.0.dist-info/METADATA
azure_mgmt_deviceupdate-1.1.0.dist-info/WHEEL
azure_mgmt_deviceupdate-1.1.0.dist-info/top_level.txt
azure_mgmt_deviceupdate-1.1.0.dist-info/RECORD
